LICENSE
MANIFEST.in
README.md
setup.cfg
setup.py
fins/__init__.py
fins/adapters.py
fins/client.py
fins/command.py
fins/exceptions.py
fins/header.py
fins/memory.py
fins/response.py
fins/response_codes.py
fins/version.py
fins_driver.egg-info/PKG-INFO
fins_driver.egg-info/SOURCES.txt
fins_driver.egg-info/dependency_links.txt
fins_driver.egg-info/not-zip-safe
fins_driver.egg-info/top_level.txt