Metadata-Version: 2.1
Name: fins-driver
Version: 0.2.0
Summary: Python FINS driver for Omron PLC
Home-page: https://github.com/indrarudianto/fins-driver
Author: Indra Rudianto
Author-email: indrarudianto.official@gmail.com
License: MIT
Classifier: Development Status :: 5 - Production/Stable
Classifier: Environment :: Console
Classifier: Operating System :: POSIX :: Linux
Classifier: Intended Audience :: Science/Research
Classifier: Natural Language :: English
Classifier: Programming Language :: Python :: 3.8
Classifier: Programming Language :: Python :: 3.9
Classifier: Programming Language :: Python :: 3.10
Classifier: Programming Language :: Python :: 3.11
Requires-Python: >=3.8
License-File: LICENSE
